jointtsmodel/JST.py
jointtsmodel/RJST.py
jointtsmodel/TSM.py
jointtsmodel/TSWE.py
jointtsmodel/__init__.py
jointtsmodel/base.py
jointtsmodel/sLDA.py
jointtsmodel/utils.py
jointtsmodel-1.6.dist-info/LICENSE
jointtsmodel-1.6.dist-info/METADATA
jointtsmodel-1.6.dist-info/WHEEL
jointtsmodel-1.6.dist-info/top_level.txt
jointtsmodel-1.6.dist-info/RECORD
