Metadata-Version: 2.1
Name: jointtsmodel
Version: 1.6
Summary: jointtsmodel - library of joint topic-sentiment models
Home-page: https://github.com/victor7246/jointtsmodel
Author: Ayan Sengupta
Author-email: ayan.sengupta007@gmail.com
License: MIT License
Platform: UNKNOWN
Requires-Dist: pandas
Requires-Dist: numpy
Requires-Dist: scipy
Requires-Dist: nltk
Requires-Dist: sklearn
